[
    {
        "title": "Projecting vectors onto a subspace of $R^n$",
        "description": "Projecting vectors onto a subspace of R^n that is defined by an orthonormal basis and creating an orthonormal basis of the span of some other orthonormal basis added by a vector that is linearly independent to it",
        "categories": "math",
        "progress": "completed",
        "length": "short",
        "url": "./vecproj.html",
        "creation_date": 1712309964
    },
    {
        "title": "All real numbers have a decimal representation",
        "description": "My attempt to prove that all real numbers have a decimal representation without much background in analysis",
        "categories": "math",
        "length": "short",
        "progress": "completed",
        "url": "./realnumdecrep.html",
        "creation_date": 1712364592
    },
    {
        "title": "Algebraic and Order Limit Theorems Exercises",
        "description": "My attempt at proving the algebraic and order limit theorems without reading the given ones on my book and doing the exercises about them on my analysis book.",
        "categories": "math",
        "progress": "completed",
        "length": "medium",
        "url": "./algeb-order-lim.html",
        "creation_date": 1715696465
    },
    {
        "title": "Show that $ln(x + 1)^2 \\geq ln(x)ln(x + 2)$",
        "description": "Showing the inequality in the title using multivariable calculus.",
        "categories": "math",
        "progress": "completed",
        "length": "short",
        "url": "ln-ineq.html",
        "creation_date": 1712661678
    },
    {
        "title": "Lagrange multipliers in multivariable calculus",
        "description": "My attempt at explaining Lagrange multipliers in multivariable calculus.",
        "categories": "math",
        "progress": "ongoing",
        "length": "medium",
        "url": "lagranmul-mvcalc.html",
        "creation_date": 1712438028
    },
    {
        "title": "Exercises on Stephen Abbott's Understanding Analysis book part 1",
        "description": "The last exercises on the first chapter of the book.",
        "categories": "math",
        "length": "long",
        "progress": "completed",
        "url": "./analysis-exercises-1.html",
        "creation_date": 1713715396
    },
    {
        "title": "Fully connected neural networks",
        "description": "My attempt at explaining fully connected neural networks for recognizing digits, a classic start for learning neural networks",
        "categories": "math, programming",
        "progress": "ongoing",
        "length": "long",
        "url": "./fcnn.html",
        "creation_date": 1712679469
    },
    {
        "title": "Brainstorm on polytopes",
        "description": "Brainstorming about polytopes. How would you formally define polytopes? How do you construct arbitrary-volume polytopes, do point-collision with them, and calculate their volume?",
        "categories": "math",
        "progress": "ongoing",
        "length": "medium",
        "url": "./mypolytope.html",
        "creation_date": 1712963845
    },
    {
        "title": "FCNN review - basic derivative framework",
        "description": "A review on FCNN focusing on making a simple derivative framework",
        "categories": "programming",
        "progress": "ongoing",
        "length": "medium",
        "url": "./basic-derivative-framework.html",
        "creation_date": 1715522900
    },
    {
        "title": "$\\epsilon-\\delta$ definition of continuity and topological definition of continuity for the reals",
        "description": "A story of me trying to prove that",
        "url": "./epsilon-delta-and-topological-continuity-equivalence.html",
        "categories": "math",
        "progress": "ongoing",
        "length": "medium",
        "creation_date": 1719935540
    },
    {
        "title": "Monotone Convergence and Infinite Series Exercises",
        "description": "Monotone Convergence and Infinite Series Exercises",
        "url": "./monoconv-and-infseries-start.html",
        "categories": "math",
        "progress": "ongoing",
        "length": "long",
        "creation_date": 1716779867
    },
    {
        "title": "A Simple Lemma of Open Maps and it's usage",
        "description": "Suppose $a < b$ is defined with $a \\in \\mathbb{R} \\cup \\{ -\\infty \\}, b \\in \\mathbb{R}$ and $f: (a, b) \to \\mathbb{R}$ is increasing and is an open map and $f((a, b)) \\subseteq (a, b)$ and $x \\in (a, b)$ implies $f(x) > x$, then if $(x_n)$ is a sequence which starts out in $(a, b)$ and is recursively defined with $f$, therefore $x_1 \\in (a, b)$ and $x_{n+1} = f(x_n)$, then $(x_n) \\to b$.",
        "url": "./specific-monotone-sequences-exact-limit.html",
        "categories": "math",
        "progress": "completed",
        "length": "short",
        "creation_date": 1720247754
    },
    {
        "title": "The convergence of sequences in the form $x_{n+1} = \\frac{1}{r-x_n}$ with $|r| \\geq 2$",
        "description": "A full investigation on the convergence of sequences in the form of The convergence of sequences in the form $x_{n+1} = \\frac{1}{r-x_n}$ with $|r| \\geq 2$",
        "url": "./recip-r-x-recurseq-convergence.html",
        "categories": "math",
        "progress": "completed",
        "length": "short",
        "creation_date": 1720034153
    }
]